Metadata-Version: 2.1
Name: cpgw
Version: 1.5.0
Summary: Cooper Gateway
Home-page: https://github.com/hardwario/cpgw
Author: HARDWARIO s.r.o.
Author-email: ask@hardwario.com
License: MIT
Keywords: cooper,cli,tool
Platform: UNKNOWN
Classifier: Development Status :: 5 - Production/Stable
Classifier: License :: OSI Approved :: MIT License
Classifier: Operating System :: OS Independent
Classifier: Programming Language :: Python
Classifier: Programming Language :: Python :: 3.6
Classifier: Topic :: Scientific/Engineering :: Human Machine Interfaces
Classifier: Environment :: Console
Classifier: Intended Audience :: Science/Research
